mili/__init__.py
mili/__main__.py
mili/_panel.py
mili/client.py
mili/pixels.py
mi_led_interface-1.0.5.dist-info/METADATA
mi_led_interface-1.0.5.dist-info/WHEEL
mi_led_interface-1.0.5.dist-info/RECORD
