Metadata-Version: 2.4
Name: mi-led-interface
Version: 1.0.5
Summary: Modular interface for controlling the Merkury Innovations LED Matrix Display via BLE.
License: MIT
Keywords: ble,bluetooth,led,matrix,hardware
Author: scooglat
Author-email: scooglat@gmail.com
Requires-Python: >=3.10,<4.0
Classifier: License :: OSI Approved :: MIT License
Classifier: Programming Language :: Python :: 3
Classifier: Programming Language :: Python :: 3.10
Classifier: Programming Language :: Python :: 3.11
Classifier: Programming Language :: Python :: 3.12
Classifier: Programming Language :: Python :: 3.13
Classifier: Programming Language :: Python :: 3.14
Requires-Dist: bleak (>=2.0.0,<3.0.0)
Requires-Dist: filetype (>=1.2.0,<2.0.0)
Requires-Dist: pillow (>=12.0.0,<13.0.0)
Project-URL: Homepage, https://github.com/the-sluggiest-cat/mi-led-interface/tree/main?tab=readme-ov-file
Project-URL: Repository, https://github.com/the-sluggiest-cat/mi-led-interface/tree/main?tab=readme-ov-file
